paramset_pyspecdata/__init__.py
paramset_pyspecdata-0.1.0.dist-info/DESCRIPTION.rst
paramset_pyspecdata-0.1.0.dist-info/METADATA
paramset_pyspecdata-0.1.0.dist-info/RECORD
paramset_pyspecdata-0.1.0.dist-info/WHEEL
paramset_pyspecdata-0.1.0.dist-info/metadata.json
paramset_pyspecdata-0.1.0.dist-info/top_level.txt
