Metadata-Version: 2.0
Name: paramset-pyspecdata
Version: 0.1.0
Summary: helper for pyspecdata
Home-page: UNKNOWN
Author: J. M. Franck
Author-email: UNKNOWN
License: LICENSE.md
Platform: UNKNOWN
